ppy_file_text/__init__.py
ppy_file_text/file/__init__.py
ppy_file_text/file/ppy_archive.py
ppy_file_text/file/ppyf_file_util.py
ppy_file_text/test/__init__.py
ppy_file_text/test/string_convert_test.py
ppy_file_text/text/__init__.py
ppy_file_text/text/ppyt_string_util.py
ppy_file_text/text/ppyt_text_file_man.py
ppy_file_text-0.0.7.dist-info/LICENSE
ppy_file_text-0.0.7.dist-info/METADATA
ppy_file_text-0.0.7.dist-info/WHEEL
ppy_file_text-0.0.7.dist-info/top_level.txt
ppy_file_text-0.0.7.dist-info/RECORD
