Metadata-Version: 2.1
Name: ppy-file-text
Version: 0.0.7
Summary: PWeb Python File & Text is a library which help to perform text read write operation with file directory manipulation
Home-page: https://github.com/banglafighter/ppy-file-text
Author: Bangla Fighter
Author-email: banglafighter.com@gmail.com
License: Apache 2.0
Platform: any
Classifier: Intended Audience :: Developers
Classifier: License :: OSI Approved :: Apache Software License
Classifier: Programming Language :: Python
License-File: LICENSE
Requires-Dist: ppy-common
